README
setup.py
utemplate/compiled.py
utemplate/source.py
utemplate.egg-info/PKG-INFO
utemplate.egg-info/SOURCES.txt
utemplate.egg-info/dependency_links.txt
utemplate.egg-info/top_level.txt