Metadata-Version: 1.0
Name: utemplate
Version: 0.9.1
Summary: Very lightweight, memory-efficient (uses generator
Home-page: https://github.com/pfalcon/utemplate
Author: Paul Sokolovsky
Author-email: pfalcon@users.sourceforge.net
License: MIT
Platform: UNKNOWN
